LICENSE
MANIFEST.in
README.md
setup.py
evpnrqdhft/__init__.py
evpnrqdhft/api_helper.py
evpnrqdhft/configuration.py
evpnrqdhft/decorators.py
evpnrqdhft/evpnrqdhft_client.py
evpnrqdhft.egg-info/PKG-INFO
evpnrqdhft.egg-info/SOURCES.txt
evpnrqdhft.egg-info/dependency_links.txt
evpnrqdhft.egg-info/requires.txt
evpnrqdhft.egg-info/top_level.txt
evpnrqdhft/controllers/__init__.py
evpnrqdhft/controllers/api_controller.py
evpnrqdhft/controllers/base_controller.py
evpnrqdhft/exceptions/__init__.py
evpnrqdhft/exceptions/api_exception.py
evpnrqdhft/http/__init__.py
evpnrqdhft/http/http_call_back.py
evpnrqdhft/http/http_client.py
evpnrqdhft/http/http_context.py
evpnrqdhft/http/http_method_enum.py
evpnrqdhft/http/http_request.py
evpnrqdhft/http/http_response.py
evpnrqdhft/http/requests_client.py
evpnrqdhft/http/auth/__init__.py
evpnrqdhft/http/auth/basic_auth.py
evpnrqdhft/models/__init__.py
evpnrqdhft/models/suite_code_enum.py
tests/__init__.py
tests/http_response_catcher.py
tests/test_helper.py
tests/controllers/__init__.py
tests/controllers/controller_test_base.py
tests/controllers/test_api_controller.py